{
    "BadgeVault": [
        {
            "name": "GD GEEK",
            "badge": "https://gb.obamabot.me/1509d0b113e91a2ec6030233c179d1da0e9e25ed.png"
        },
        {
            "name": "🗿",
            "badge": "https://gb.obamabot.me/3d63d7e8e9dadfc9a0e706e509e33a742bcd5f6f.png"
        },
        {
            "name": "Splatoon Player",
            "badge": "https://gb.obamabot.me/a2bab8b878b14afff7504473cb95f8d0345b460d.png"
        },
        {
            "name": "OG player",
            "badge": "https://gb.obamabot.me/07845c5cb9f85a481b0eb37d56e7c5fd9be23322.png"
        },
        {
            "name": "ZenWars Owner",
            "badge": "https://gb.obamabot.me/b572e052a4733ed37604aaa9bcb1bf90b4594faf.gif"
        }
    ]
}