{
    "BadgeVault": [
        {
            "name": "Why do we all have to wear these ridiculous ties?",
            "badge": "https://gb.obamabot.me/c7e65b357583a563fb256d4c33cb4217bc3b2416.png"
        },
        {
            "name": "Demo",
            "badge": "https://gb.obamabot.me/bef7ec49c9eb5bf58da3f0aa2d3131647f729483.gif"
        },
        {
            "name": "Agony",
            "badge": "https://gb.obamabot.me/063f0937722b8d9bce7864c4d06edad572fa4a8e.gif"
        },
        {
            "name": "RSX has left the chat",
            "badge": "https://gb.obamabot.me/45dcc9ab40ed60e7079a1e83332e271ab9ffb284.png"
        },
        {
            "name": "Currently playing: Half-life 2 Chapter 1",
            "badge": "https://gb.obamabot.me/39b21fa80531b7660a109c8024c866def1d6a6a3.png"
        }
    ]
}