{
    "BadgeVault": [
        {
            "name": "Aitaquine",
            "badge": "https://gb.obamabot.me/0c59418e9446d3c343b74c8a1ea0f5d9f3c24675.webp"
        },
        {
            "name": "Kek",
            "badge": "https://gb.obamabot.me/8446fdb166904616d01a6abde9b12d64caae0b4e.webp"
        },
        {
            "name": "Aitrain",
            "badge": "https://gb.obamabot.me/be3f3d91fe460ca8d719f4ba6876e84dd539a75a.gif"
        },
        {
            "name": "cafkekw",
            "badge": "https://gb.obamabot.me/57a4771d56053f7fa3986e4bfca55dc032e19b90.webp"
        },
        {
            "name": "Ai",
            "badge": "https://gb.obamabot.me/56282715cf8de9f5c81accdf9cc72a38a9036f23.webp"
        }
    ]
}